<?xml version="1.0" encoding="UTF-8"?>
<con:soapui-project id="ab295b2b-804c-48cb-85e8-a1923b0a106e" activeEnvironment="Default" name="REST Project 1" resourceRoot="" soapui-version="5.6.0" abortOnError="false" runType="SEQUENTIAL" xmlns:con="http://eviware.com/soapui/config"><con:settings/><con:interface xsi:type="con:RestService" id="e2057981-3685-4137-9b0d-5938c538e740" wadlVersion="http://wadl.dev.java.net/2009/02" name="https://restcountries.eu" type="rest" xmlns:xsi="http://www.w3.org/2001/XMLSchema-instance"><con:settings/><con:definitionCache type="TEXT" rootPart=""/><con:endpoints><con:endpoint>https://restcountries.eu</con:endpoint></con:endpoints><con:resource name="All" path="/rest/v2/all" id="ae4d5e86-07e1-4c6a-8f83-0f45aea9806d"><con:settings/><con:parameters/><con:method name="All 1" id="3e5cb9ae-7a11-4fa2-961c-f0addf3e97b2" method="GET"><con:settings/><con:parameters/><con:representation type="RESPONSE"><con:mediaType>application/json;charset=utf-8</con:mediaType><con:status>200</con:status><con:params/><con:element>Response</con:element></con:representation><con:request name="Request 1" id="d1b2793d-95dd-49d3-8177-f5ea2eaae9ff" mediaType="application/json"><con:settings><con:setting id="com.eviware.soapui.impl.wsdl.WsdlRequest@request-headers">&lt;xml-fragment/></con:setting></con:settings><con:endpoint>https://restcountries.eu</con:endpoint><con:request/><con:originalUri>https://restcountries.eu/rest/v2/all</con:originalUri><con:credentials><con:authType>No Authorization</con:authType></con:credentials><con:jmsConfig JMSDeliveryMode="PERSISTENT"/><con:jmsPropertyConfig/><con:parameters/></con:request></con:method></con:resource></con:interface><con:interface xsi:type="con:RestService" id="172bf310-4436-45b7-a611-23abbc684e45" wadlVersion="http://wadl.dev.java.net/2009/02" name="https://restcountries.eu" type="rest" xmlns:xsi="http://www.w3.org/2001/XMLSchema-instance"><con:settings/><con:definitionCache type="TEXT" rootPart=""/><con:endpoints><con:endpoint>https://restcountries.eu</con:endpoint></con:endpoints><con:resource name="United" path="/rest/v2/name/{countryName}" id="21ca6990-213d-4ad0-add8-a5fae6f0c7ba"><con:settings/><con:parameters><con:parameter><con:name>countryName</con:name><con:value/><con:style>TEMPLATE</con:style><con:default/><con:description xsi:nil="true"/></con:parameter></con:parameters><con:method name="United 1" id="046b815d-8eaf-4c21-bd6c-8c6ce2f38300" method="GET"><con:settings/><con:parameters/><con:representation type="RESPONSE"><con:mediaType>application/json;charset=utf-8</con:mediaType><con:status>200</con:status><con:params/><con:element>Response</con:element></con:representation><con:request name="Request 1" id="352c5f1c-5abe-4ddf-a576-04127fd4b624" mediaType="application/json"><con:settings><con:setting id="com.eviware.soapui.impl.wsdl.WsdlRequest@request-headers">&lt;xml-fragment/></con:setting></con:settings><con:endpoint>https://restcountries.eu</con:endpoint><con:request/><con:originalUri>https://restcountries.eu/rest/v2/name/united</con:originalUri><con:credentials><con:authType>No Authorization</con:authType></con:credentials><con:jmsConfig JMSDeliveryMode="PERSISTENT"/><con:jmsPropertyConfig/><con:parameters><entry key="countryName" value="india" xmlns="http://eviware.com/soapui/config"/></con:parameters><con:parameterOrder><con:entry>countryName</con:entry></con:parameterOrder></con:request></con:method></con:resource></con:interface><con:interface xsi:type="con:RestService" id="17bc61fd-ab3f-4f7b-b4e7-e3a2ac30d87e" wadlVersion="http://wadl.dev.java.net/2009/02" name="https://restcountries.eu" type="rest" xmlns:xsi="http://www.w3.org/2001/XMLSchema-instance"><con:settings/><con:definitionCache/><con:endpoints><con:endpoint>https://restcountries.eu</con:endpoint></con:endpoints><con:resource name="Aruba" path="/rest/v2/name/aruba" id="ab7d767d-d25b-4b96-850f-02f26818cacb"><con:settings/><con:parameters><con:parameter><con:name>fullText</con:name><con:value>true</con:value><con:style>QUERY</con:style><con:default>true</con:default><con:path xsi:nil="true"/><con:description xsi:nil="true"/></con:parameter></con:parameters><con:method name="Aruba 1" id="8981e80d-6daa-4d2f-bd22-c905a121be87" method="GET"><con:settings/><con:parameters/><con:representation type="RESPONSE"><con:mediaType>application/json;charset=utf-8</con:mediaType><con:status>200</con:status><con:params/><con:element>Response</con:element></con:representation><con:request name="Request 1" id="a17379e1-3428-4dd9-8995-98c288a373c3" mediaType="application/json"><con:settings><con:setting id="com.eviware.soapui.impl.wsdl.WsdlRequest@request-headers">&lt;xml-fragment/></con:setting></con:settings><con:endpoint>https://restcountries.eu</con:endpoint><con:request/><con:originalUri>https://restcountries.eu/rest/v2/name/aruba</con:originalUri><con:credentials><con:authType>No Authorization</con:authType></con:credentials><con:jmsConfig JMSDeliveryMode="PERSISTENT"/><con:jmsPropertyConfig/><con:parameters><entry key="fullText" value="false" xmlns="http://eviware.com/soapui/config"/></con:parameters><con:parameterOrder><con:entry>fullText</con:entry></con:parameterOrder></con:request></con:method></con:resource></con:interface><con:testSuite id="bf095c12-0301-4bc5-9acd-674f28d016d4" name="TestSuite2"><con:settings/><con:runType>SEQUENTIAL</con:runType><con:testCase id="2651ca0e-067f-40e1-b8b0-ad18b4b6c855" failOnError="true" failTestCaseOnErrors="true" keepSession="false" maxResults="0" name="TestCase1" searchProperties="true"><con:settings/><con:testStep type="restrequest" name="getAllCountries" id="848f2238-d1bc-4da1-8a05-cef4fd9417b5"><con:settings/><con:config service="https://restcountries.eu" resourcePath="/rest/v2/all" methodName="All 1" xsi:type="con:RestRequestStep" xmlns:xsi="http://www.w3.org/2001/XMLSchema-instance"><con:restRequest name="getAllCountries" id="d1b2793d-95dd-49d3-8177-f5ea2eaae9ff" mediaType="application/json"><con:settings><con:setting id="com.eviware.soapui.impl.wsdl.WsdlRequest@request-headers">&lt;xml-fragment/></con:setting></con:settings><con:endpoint>https://restcountries.eu</con:endpoint><con:request/><con:originalUri>https://restcountries.eu/rest/v2/all</con:originalUri><con:assertion type="Simple Contains" id="6e730de3-945c-4aff-b366-6c010dc3e2dc" name="Contains"><con:configuration><token>Europe</token><ignoreCase>false</ignoreCase><useRegEx>false</useRegEx></con:configuration></con:assertion><con:credentials><con:authType>No Authorization</con:authType></con:credentials><con:jmsConfig JMSDeliveryMode="PERSISTENT"/><con:jmsPropertyConfig/><con:parameters/></con:restRequest></con:config></con:testStep><con:testStep type="restrequest" name="GetDetailsByCountryName" id="5f61d103-715c-4bc3-a8b1-0109ddbb1731"><con:settings/><con:config service="https://restcountries.eu" resourcePath="/rest/v2/name/{countryName}" methodName="United 1" xsi:type="con:RestRequestStep" xmlns:xsi="http://www.w3.org/2001/XMLSchema-instance"><con:restRequest name="GetDetailsByCountryName" id="352c5f1c-5abe-4ddf-a576-04127fd4b624" mediaType="application/json"><con:settings><con:setting id="com.eviware.soapui.impl.wsdl.WsdlRequest@request-headers">&lt;xml-fragment/></con:setting></con:settings><con:endpoint>https://restcountries.eu</con:endpoint><con:request/><con:originalUri>https://restcountries.eu/rest/v2/name/united</con:originalUri><con:assertion type="Simple Contains" id="79ec9e1e-a119-494a-930d-812e17ad6fce" name="Contains"><con:configuration><token>Indian</token><ignoreCase>false</ignoreCase><useRegEx>false</useRegEx></con:configuration></con:assertion><con:credentials><con:authType>No Authorization</con:authType></con:credentials><con:jmsConfig JMSDeliveryMode="PERSISTENT"/><con:jmsPropertyConfig/><con:parameters><entry key="countryName" value="india" xmlns="http://eviware.com/soapui/config"/></con:parameters><con:parameterOrder><con:entry>countryName</con:entry></con:parameterOrder></con:restRequest></con:config></con:testStep><con:testStep type="groovy" name="setUptearDownGroovy" id="516dd332-8408-4fee-9d22-746d5c1f5a3b"><con:settings/><con:config><script>testRunner.testCase.testSuite.project.getTestSuiteByName('TestSuite1').getTestCaseByName('TestCase1').setSetupScript('log.info "setup testcase"')
testRunner.testCase.testSuite.project.getTestSuiteByName('TestSuite1').getTestCaseByName('TestCase1').setTearDownScript('log.info "teardown testcase"')

testRunner.testCase.testSuite.project.getTestSuiteByName('TestSuite1').setSetupScript('log.info "setup tsetsuite"')
testRunner.testCase.testSuite.project.getTestSuiteByName('TestSuite1').setTearDownScript('log.info "teardown testsuite"')

//testRunner.testCase.testSuite.project.setSetupScript('log.info "setup project"')
//testRunner.testCase.testSuite.project.setTearDownScript('log.info "teardown project"')

log.info ("  --  "+testRunner.testCase.getSetupScript());
log.info ("  --  "+testRunner.testCase.getTearDownScript());

log.info ("  --  "+testRunner.testCase.testSuite.getSetupScript());
log.info ("  --  "+testRunner.testCase.testSuite.getTearDownScript());

//log.info ("  --  "+testRunner.testCase.testSuite.project.getSetupScript());
//log.info ("  --  "+testRunner.testCase.testSuite.project.getTearDownScript());</script></con:config></con:testStep><con:setupScript>log.info "setup testcase"</con:setupScript><con:tearDownScript>log.info "teardown testcase"</con:tearDownScript><con:properties><con:property><con:name>countryName</con:name><con:value>United States</con:value></con:property><con:property><con:name>countryCode</con:name><con:value>US</con:value></con:property></con:properties></con:testCase><con:testCase id="8a2b005e-e373-43cf-8104-31b649a7917e" failOnError="true" failTestCaseOnErrors="true" keepSession="false" maxResults="0" name="GetCountryName" searchProperties="true"><con:settings/><con:testStep type="restrequest" name="All" id="2aacc8e7-456c-4ce5-97c3-a521e48d556d"><con:settings/><con:config service="https://restcountries.eu" resourcePath="/rest/v2/all" methodName="All 1" xsi:type="con:RestRequestStep" xmlns:xsi="http://www.w3.org/2001/XMLSchema-instance"><con:restRequest name="All" id="d1b2793d-95dd-49d3-8177-f5ea2eaae9ff" mediaType="application/json"><con:settings><con:setting id="com.eviware.soapui.impl.wsdl.WsdlRequest@request-headers">&lt;xml-fragment/></con:setting></con:settings><con:endpoint>https://restcountries.eu</con:endpoint><con:request/><con:originalUri>https://restcountries.eu/rest/v2/all</con:originalUri><con:assertion type="JsonPath Count" id="db4c5ed8-8740-4f7b-acdf-51684aae8fdc" name="JsonPath Count"><con:configuration><path>[2].languages[0].name</path><content>1</content><allowWildcards>false</allowWildcards><ignoreNamspaceDifferences>false</ignoreNamspaceDifferences><ignoreComments>false</ignoreComments></con:configuration></con:assertion><con:assertion type="JsonPath Match" id="1014905f-3f9b-4bfa-b661-c7fe78530cb7" name="JsonPath Match"><con:configuration><path>[1].languages[0].name</path><content>Swedish</content><allowWildcards>false</allowWildcards><ignoreNamspaceDifferences>false</ignoreNamspaceDifferences><ignoreComments>false</ignoreComments></con:configuration></con:assertion><con:assertion type="JsonPath Existence Match" id="7468bdcd-135e-443c-8851-79e0d3677ab9" name="JsonPath Existence Match"><con:configuration><path>[1].currencies[0].name</path><content>true</content><allowWildcards>false</allowWildcards><ignoreNamspaceDifferences>false</ignoreNamspaceDifferences><ignoreComments>false</ignoreComments></con:configuration></con:assertion><con:assertion type="JsonPath RegEx Match" id="08f6eb71-861b-48b3-9b97-505247a2dcb7" name="JsonPath RegEx Match"><con:configuration><path>[3].languages[0].name</path><content>true</content><allowWildcards>false</allowWildcards><ignoreNamspaceDifferences>false</ignoreNamspaceDifferences><ignoreComments>false</ignoreComments><regEx>Arabic</regEx></con:configuration></con:assertion><con:credentials><con:authType>No Authorization</con:authType></con:credentials><con:jmsConfig JMSDeliveryMode="PERSISTENT"/><con:jmsPropertyConfig/><con:parameters/></con:restRequest></con:config></con:testStep><con:properties/></con:testCase><con:properties><con:property><con:name>countryName</con:name><con:value>Argentina</con:value></con:property></con:properties><con:setupScript>log.info "setup tsetsuite"</con:setupScript><con:tearDownScript>log.info "teardown testsuite"</con:tearDownScript></con:testSuite><con:testSuite id="3c529445-aaeb-4521-a408-c356917cd911" name="Testsuite1"><con:description>TestSuite generated for REST Service [https://restcountries.eu]</con:description><con:settings/><con:runType>SEQUENTIAL</con:runType><con:testCase id="2824f60c-a45b-4547-a2c0-3520a0cbe898" failOnError="true" failTestCaseOnErrors="true" keepSession="false" maxResults="0" name="https://restcountries.eu TestSuite" searchProperties="true"><con:settings/><con:testStep type="restrequest" name="All" id="7729617f-cab8-47fb-bf25-8df0ab60bf16"><con:settings/><con:config service="https://restcountries.eu" resourcePath="/rest/v2/all" methodName="All 1" xsi:type="con:RestRequestStep" xmlns:xsi="http://www.w3.org/2001/XMLSchema-instance"><con:restRequest name="All" id="d1b2793d-95dd-49d3-8177-f5ea2eaae9ff" mediaType="application/json"><con:settings><con:setting id="com.eviware.soapui.impl.wsdl.WsdlRequest@request-headers">&lt;xml-fragment/></con:setting></con:settings><con:endpoint>https://restcountries.eu</con:endpoint><con:request/><con:originalUri>https://restcountries.eu/rest/v2/all</con:originalUri><con:assertion type="JsonPath Count" id="db4c5ed8-8740-4f7b-acdf-51684aae8fdc" name="JsonPath Count"><con:configuration><path>[2].languages[0].name</path><content>1</content><allowWildcards>false</allowWildcards><ignoreNamspaceDifferences>false</ignoreNamspaceDifferences><ignoreComments>false</ignoreComments></con:configuration></con:assertion><con:assertion type="JsonPath Match" id="1014905f-3f9b-4bfa-b661-c7fe78530cb7" name="JsonPath Match"><con:configuration><path>[1].languages[0].name</path><content>Swedish</content><allowWildcards>false</allowWildcards><ignoreNamspaceDifferences>false</ignoreNamspaceDifferences><ignoreComments>false</ignoreComments></con:configuration></con:assertion><con:assertion type="JsonPath Existence Match" id="7468bdcd-135e-443c-8851-79e0d3677ab9" name="JsonPath Existence Match"><con:configuration><path>[1].currencies[0].name</path><content>true</content><allowWildcards>false</allowWildcards><ignoreNamspaceDifferences>false</ignoreNamspaceDifferences><ignoreComments>false</ignoreComments></con:configuration></con:assertion><con:assertion type="JsonPath RegEx Match" id="08f6eb71-861b-48b3-9b97-505247a2dcb7" name="JsonPath RegEx Match"><con:configuration><path>[3].languages[0].name</path><content>true</content><allowWildcards>false</allowWildcards><ignoreNamspaceDifferences>false</ignoreNamspaceDifferences><ignoreComments>false</ignoreComments><regEx>Arabic</regEx></con:configuration></con:assertion><con:credentials><con:authType>No Authorization</con:authType></con:credentials><con:jmsConfig JMSDeliveryMode="PERSISTENT"/><con:jmsPropertyConfig/><con:parameters/></con:restRequest></con:config></con:testStep><con:properties/></con:testCase><con:properties/></con:testSuite><con:properties><con:property><con:name>countryName</con:name><con:value>India</con:value></con:property><con:property><con:name>countryCode</con:name><con:value>IN</con:value></con:property></con:properties><con:afterLoadScript>def su = new File("C:/Users/eppsri/Desktop/usha notes/setup.txt").text
def td  = new File("C:/Users/eppsri/Desktop/usha notes/teardown.txt").text

project.getTestSuiteList().each { testSuite -
 testSuite.getTestCaseList().each { testCase -
  testCase.setSetupScript(su)
  testCase.setTearDownScript(td)
 }
}</con:afterLoadScript><con:wssContainer/><con:oAuth2ProfileContainer/><con:oAuth1ProfileContainer/><con:beforeRunScript>log.info("this executes before all test suites")</con:beforeRunScript><con:afterRunScript>log.info("this executes after all test suites")</con:afterRunScript><con:sensitiveInformation/></con:soapui-project>